{"name":"TOEFL","postlist":[{"title":"写在 TFT 小组 第 35 期 之后","slug":"after-tft-25","date":"2016-06-29T00:51:02.000Z","updated":"2018-04-12T21:41:48.000Z","comments":true,"path":"api/articles/after-tft-25.json","excerpt":"<p>在同学的介绍下，我报名了 <em>刘功勋</em> 老师的 TFT 35 期口语小组。之所以报名这个小组，理由也很简单 —— 就是为了学习口语，为 TOEFL 做准备。在昨天，小组正式结束，感觉收获颇多。同时，这几天又有一些其它想法涌上心头。</p>","keywords":null,"content":null,"raw":null,"categories":[{"name":"TOEFL","path":"api/categories/TOEFL.json"}],"tags":[{"name":"TOEFL","path":"api/tags/TOEFL.json"},{"name":"TFT","path":"api/tags/TFT.json"}]},{"title":"晴天 — TOEFL @ ZJU","slug":"toefl-10-29-zju","date":"2016-10-30T03:37:57.000Z","updated":"2018-04-12T21:44:29.000Z","comments":true,"path":"api/articles/toefl-10-29-zju.json","excerpt":"<h1 id=\"考前\"><a href=\"#考前\" class=\"headerlink\" title=\"考前\"></a>考前</h1><p>上一次考托福，考了 93。 这分数明显不够，上次出分立即报了一次。故意选择了跟上次一样的考场 — 浙大 E 考场，原因是不想去熟悉新考场了，找个已经去过的考场吧。</p>\n<p>在酒店里发生了一件小插曲，隔壁间的客户发现他们的卡不能打开房门，于是用我房间里的电话向前台求助。关键是这两位，同时也是一对情侣，也是到浙大考托福的，而且是从上海交大来的。女生表现比较开朗，在过程中了解到女生已经考出来了，而男生的成绩不理想，所以她只是陪男生来考试的。短暂的聊天中，并没提到女生的具体分数，但我猜她的分数应该还是比较不错的，因为她说了一句：“TOEFL 分数不需要很高，105 就已经足够了”。</p>","keywords":null,"content":null,"raw":null,"categories":[{"name":"TOEFL","path":"api/categories/TOEFL.json"}],"tags":[{"name":"TOEFL","path":"api/tags/TOEFL.json"}]}]}